compete/__init__.py
tests/__init__.py
compete-0.0.1.dist-info/LICENSE
compete-0.0.1.dist-info/METADATA
compete-0.0.1.dist-info/WHEEL
compete-0.0.1.dist-info/top_level.txt
compete-0.0.1.dist-info/RECORD
