Metadata-Version: 2.1
Name: compete
Version: 0.0.1
Summary: Competitive Coding in Python!
Home-page: https://github.com/ScalerAcademy/py-compete
Author: Pragy Agarwal
Author-email: agar.pragy@gmail.com
License: UNKNOWN
Platform: UNKNOWN
Classifier: Development Status :: 1 - Planning
Classifier: Environment :: Console
Classifier: Intended Audience :: Education
Classifier: License :: OSI Approved :: GNU General Public License v3 or later (GPLv3+)
Classifier: Natural Language :: English
Classifier: Programming Language :: Python :: 3
Classifier: Operating System :: OS Independent
Requires-Python: >=3.4
